BerryEasy/BerryEasy.py
BerryEasy/BerryEasyGPU.py
BerryEasy/__init__.py
BerryEasy-0.2.1.dist-info/LICENSE.txt
BerryEasy-0.2.1.dist-info/METADATA
BerryEasy-0.2.1.dist-info/WHEEL
BerryEasy-0.2.1.dist-info/top_level.txt
BerryEasy-0.2.1.dist-info/RECORD
