Metadata-Version: 2.1
Name: BerryEasy
Version: 0.2.1
Summary: A package for computing topological properties of TB models
Author-email: Alex Tyner <alextyner@gmail.com>
Project-URL: Homepage, https://github.com/actyner
Classifier: Programming Language :: Python :: 3
Classifier: License :: OSI Approved :: MIT License
Classifier: Operating System :: OS Independent
Requires-Python: >=3.7
License-File: LICENSE.txt
Requires-Dist: numpy
Requires-Dist: pybinding
Requires-Dist: matplotlib
Requires-Dist: tqdm
